lab02/adder.v
module  adder(a, b, c, d, sum, ov);
  input [3:0] a, b ,c ,d;
  output [3:0] sum;
  output ov;
  wire s1 ,s2 ,s3;

  assign {s1, s2, s3, sum} = a + b + c + d;
  assign ov = 1'b0;

endmodule

lab02/lab02_testbench_adder.v
`timescale 1ns / 1ps
module testbench_adder;

reg [3:0] a, b,c ,d;
wire [3:0] sum;
wire ov;
reg clk;
reg	rst;
reg [6:0] correct_sum;
reg [6:0] test_num;
reg correct_ov;

always #5 clk = ~clk;
always #5 rst = ~rst;

adder DUT(a, b, c, d, sum, ov);

initial
begin
	clk <= 0;
	rst <= 0;
	a <= 0; 
	b <= 0;
	c <= 0;
	d <= 0;
	test_num <= 0;
	$dumpfile("adder.vcd");
	$dumpvars;
end

always@(posedge clk or negedge rst)
begin
	if(rst)begin
		if(a <= 15) begin 
			a <= a + 1;
			test_num <= test_num + 1;
		end 
		if(a ==15) begin
			a <= 0;
			b <= b + 1;
		end
	end
	else begin
		{correct_ov, correct_sum} = a + b;
		if({ov, sum} == {correct_ov, correct_sum}) begin
			$display ("Test %d ", test_num);
			$display ("OK!");
			/*
			$display ("%d + %d = ?", a, b);
			$display ("your answer: ov = %d, sum = %d", ov, sum);
			$display ("correct answer: ov = %d, sum = %d", ov, sum);
			$display ("\n");
			*/
		end
		else begin
			$display ("Test %d ", test_num);
			$display ("/////////////////////");
			$display ("////////Fail!////////");
			$display ("/////////////////////");
			$display ("%d + %d + %d + %d = ?", a, b, c, d);
			$display ("your answer: ov = %d, sum = %d", ov, sum);
			$display ("correct answer: ov = %d, sum = %d", correct_ov, correct_sum);
			$display ("\n");
		end
	end
end
initial #1005 $finish;
endmodule

lab02/adder.vcd
$date
	Sat Mar 21 17:10:46 2020
$end
$version
	Icarus Verilog
$end
$timescale
	1ps
$end
$scope module testbench_adder $end
$var wire 1 ! ov $end
$var wire 4 " sum [3:0] $end
$var reg 4 # a [3:0] $end
$var reg 4 $ b [3:0] $end
$var reg 4 % c [3:0] $end
$var reg 1 & clk $end
$var reg 1 ' correct_ov $end
$var reg 7 ( correct_sum [6:0] $end
$var reg 4 ) d [3:0] $end
$var reg 1 * rst $end
$var reg 7 + test_num [6:0] $end
$scope module DUT $end
$var wire 4 , a [3:0] $end
$var wire 4 - b [3:0] $end
$var wire 4 . c [3:0] $end
$var wire 4 / d [3:0] $end
$var wire 1 ! ov $end
$var wire 4 0 sum [3:0] $end
$var wire 1 1 s3 $end
$var wire 1 2 s2 $end
$var wire 1 3 s1 $end
$upscope $end
$upscope $end
$enddefinitions $end
#0
$dumpvars
03
02
01
b0 0
b0 /
b0 .
b0 -
b0 ,
b0 +
0*
b0 )
b0 (
0'
0&
b0 %
b0 $
b0 #
b0 "
0!
$end
#5000
b1 "
b1 0
b1 +
b1 #
b1 ,
1*
1&
#10000
b1 (
0*
0&
#15000
b10 "
b10 0
b10 +
b10 #
b10 ,
1*
1&
#20000
b10 (
0*
0&
#25000
b11 "
b11 0
b11 +
b11 #
b11 ,
1*
1&
#30000
b11 (
0*
0&
#35000
b100 "
b100 0
b100 +
b100 #
b100 ,
1*
1&
#40000
b100 (
0*
0&
#45000
b101 "
b101 0
b101 +
b101 #
b101 ,
1*
1&
#50000
b101 (
0*
0&
#55000
b110 "
b110 0
b110 +
b110 #
b110 ,
1*
1&
#60000
b110 (
0*
0&
#65000
b111 "
b111 0
b111 +
b111 #
b111 ,
1*
1&
#70000
b111 (
0*
0&
#75000
b1000 "
b1000 0
b1000 +
b1000 #
b1000 ,
1*
1&
#80000
b1000 (
0*
0&
#85000
b1001 "
b1001 0
b1001 +
b1001 #
b1001 ,
1*
1&
#90000
b1001 (
0*
0&
#95000
b1010 "
b1010 0
b1010 +
b1010 #
b1010 ,
1*
1&
#100000
b1010 (
0*
0&
#105000
b1011 "
b1011 0
b1011 +
b1011 #
b1011 ,
1*
1&
#110000
b1011 (
0*
0&
#115000
b1100 "
b1100 0
b1100 +
b1100 #
b1100 ,
1*
1&
#120000
b1100 (
0*
0&
#125000
b1101 "
b1101 0
b1101 +
b1101 #
b1101 ,
1*
1&
#130000
b1101 (
0*
0&
#135000
b1110 "
b1110 0
b1110 +
b1110 #
b1110 ,
1*
1&
#140000
b1110 (
0*
0&
#145000
b1111 "
b1111 0
b1111 +
b1111 #
b1111 ,
1*
1&
#150000
b1111 (
0*
0&
#155000
b1 "
b1 0
b1 $
b1 -
b10000 +
b0 #
b0 ,
1*
1&
#160000
b1 (
0*
0&
#165000
b10 "
b10 0
b10001 +
b1 #
b1 ,
1*
1&
#170000
b10 (
0*
0&
#175000
b11 "
b11 0
b10010 +
b10 #
b10 ,
1*
1&
#180000
b11 (
0*
0&
#185000
b100 "
b100 0
b10011 +
b11 #
b11 ,
1*
1&
#190000
b100 (
0*
0&
#195000
b101 "
b101 0
b10100 +
b100 #
b100 ,
1*
1&
#200000
b101 (
0*
0&
#205000
b110 "
b110 0
b10101 +
b101 #
b101 ,
1*
1&
#210000
b110 (
0*
0&
#215000
b111 "
b111 0
b10110 +
b110 #
b110 ,
1*
1&
#220000
b111 (
0*
0&
#225000
b1000 "
b1000 0
b10111 +
b111 #
b111 ,
1*
1&
#230000
b1000 (
0*
0&
#235000
b1001 "
b1001 0
b11000 +
b1000 #
b1000 ,
1*
1&
#240000
b1001 (
0*
0&
#245000
b1010 "
b1010 0
b11001 +
b1001 #
b1001 ,
1*
1&
#250000
b1010 (
0*
0&
#255000
b1011 "
b1011 0
b11010 +
b1010 #
b1010 ,
1*
1&
#260000
b1011 (
0*
0&
#265000
b1100 "
b1100 0
b11011 +
b1011 #
b1011 ,
1*
1&
#270000
b1100 (
0*
0&
#275000
b1101 "
b1101 0
b11100 +
b1100 #
b1100 ,
1*
1&
#280000
b1101 (
0*
0&
#285000
b1110 "
b1110 0
b11101 +
b1101 #
b1101 ,
1*
1&
#290000
b1110 (
0*
0&
#295000
b1111 "
b1111 0
b11110 +
b1110 #
b1110 ,
1*
1&
#300000
b1111 (
0*
0&
#305000
b0 "
b0 0
11
b11111 +
b1111 #
b1111 ,
1*
1&
#310000
b10000 (
0*
0&
#315000
b10 "
b10 0
01
b10 $
b10 -
b100000 +
b0 #
b0 ,
1*
1&
#320000
b10 (
0*
0&
#325000
b11 "
b11 0
b100001 +
b1 #
b1 ,
1*
1&
#330000
b11 (
0*
0&
#335000
b100 "
b100 0
b100010 +
b10 #
b10 ,
1*
1&
#340000
b100 (
0*
0&
#345000
b101 "
b101 0
b100011 +
b11 #
b11 ,
1*
1&
#350000
b101 (
0*
0&
#355000
b110 "
b110 0
b100100 +
b100 #
b100 ,
1*
1&
#360000
b110 (
0*
0&
#365000
b111 "
b111 0
b100101 +
b101 #
b101 ,
1*
1&
#370000
b111 (
0*
0&
#375000
b1000 "
b1000 0
b100110 +
b110 #
b110 ,
1*
1&
#380000
b1000 (
0*
0&
#385000
b1001 "
b1001 0
b100111 +
b111 #
b111 ,
1*
1&
#390000
b1001 (
0*
0&
#395000
b1010 "
b1010 0
b101000 +
b1000 #
b1000 ,
1*
1&
#400000
b1010 (
0*
0&
#405000
b1011 "
b1011 0
b101001 +
b1001 #
b1001 ,
1*
1&
#410000
b1011 (
0*
0&
#415000
b1100 "
b1100 0
b101010 +
b1010 #
b1010 ,
1*
1&
#420000
b1100 (
0*
0&
#425000
b1101 "
b1101 0
b101011 +
b1011 #
b1011 ,
1*
1&
#430000
b1101 (
0*
0&
#435000
b1110 "
b1110 0
b101100 +
b1100 #
b1100 ,
1*
1&
#440000
b1110 (
0*
0&
#445000
b1111 "
b1111 0
b101101 +
b1101 #
b1101 ,
1*
1&
#450000
b1111 (
0*
0&
#455000
b0 "
b0 0
11
b101110 +
b1110 #
b1110 ,
1*
1&
#460000
b10000 (
0*
0&
#465000
b1 "
b1 0
b101111 +
b1111 #
b1111 ,
1*
1&
#470000
b10001 (
0*
0&
#475000
b11 "
b11 0
01
b11 $
b11 -
b110000 +
b0 #
b0 ,
1*
1&
#480000
b11 (
0*
0&
#485000
b100 "
b100 0
b110001 +
b1 #
b1 ,
1*
1&
#490000
b100 (
0*
0&
#495000
b101 "
b101 0
b110010 +
b10 #
b10 ,
1*
1&
#500000
b101 (
0*
0&
#505000
b110 "
b110 0
b110011 +
b11 #
b11 ,
1*
1&
#510000
b110 (
0*
0&
#515000
b111 "
b111 0
b110100 +
b100 #
b100 ,
1*
1&
#520000
b111 (
0*
0&
#525000
b1000 "
b1000 0
b110101 +
b101 #
b101 ,
1*
1&
#530000
b1000 (
0*
0&
#535000
b1001 "
b1001 0
b110110 +
b110 #
b110 ,
1*
1&
#540000
b1001 (
0*
0&
#545000
b1010 "
b1010 0
b110111 +
b111 #
b111 ,
1*
1&
#550000
b1010 (
0*
0&
#555000
b1011 "
b1011 0
b111000 +
b1000 #
b1000 ,
1*
1&
#560000
b1011 (
0*
0&
#565000
b1100 "
b1100 0
b111001 +
b1001 #
b1001 ,
1*
1&
#570000
b1100 (
0*
0&
#575000
b1101 "
b1101 0
b111010 +
b1010 #
b1010 ,
1*
1&
#580000
b1101 (
0*
0&
#585000
b1110 "
b1110 0
b111011 +
b1011 #
b1011 ,
1*
1&
#590000
b1110 (
0*
0&
#595000
b1111 "
b1111 0
b111100 +
b1100 #
b1100 ,
1*
1&
#600000
b1111 (
0*
0&
#605000
b0 "
b0 0
11
b111101 +
b1101 #
b1101 ,
1*
1&
#610000
b10000 (
0*
0&
#615000
b1 "
b1 0
b111110 +
b1110 #
b1110 ,
1*
1&
#620000
b10001 (
0*
0&
#625000
b10 "
b10 0
b111111 +
b1111 #
b1111 ,
1*
1&
#630000
b10010 (
0*
0&
#635000
b100 "
b100 0
01
b100 $
b100 -
b1000000 +
b0 #
b0 ,
1*
1&
#640000
b100 (
0*
0&
#645000
b101 "
b101 0
b1000001 +
b1 #
b1 ,
1*
1&
#650000
b101 (
0*
0&
#655000
b110 "
b110 0
b1000010 +
b10 #
b10 ,
1*
1&
#660000
b110 (
0*
0&
#665000
b111 "
b111 0
b1000011 +
b11 #
b11 ,
1*
1&
#670000
b111 (
0*
0&
#675000
b1000 "
b1000 0
b1000100 +
b100 #
b100 ,
1*
1&
#680000
b1000 (
0*
0&
#685000
b1001 "
b1001 0
b1000101 +
b101 #
b101 ,
1*
1&
#690000
b1001 (
0*
0&
#695000
b1010 "
b1010 0
b1000110 +
b110 #
b110 ,
1*
1&
#700000
b1010 (
0*
0&
#705000
b1011 "
b1011 0
b1000111 +
b111 #
b111 ,
1*
1&
#710000
b1011 (
0*
0&
#715000
b1100 "
b1100 0
b1001000 +
b1000 #
b1000 ,
1*
1&
#720000
b1100 (
0*
0&
#725000
b1101 "
b1101 0
b1001001 +
b1001 #
b1001 ,
1*
1&
#730000
b1101 (
0*
0&
#735000
b1110 "
b1110 0
b1001010 +
b1010 #
b1010 ,
1*
1&
#740000
b1110 (
0*
0&
#745000
b1111 "
b1111 0
b1001011 +
b1011 #
b1011 ,
1*
1&
#750000
b1111 (
0*
0&
#755000
b0 "
b0 0
11
b1001100 +
b1100 #
b1100 ,
1*
1&
#760000
b10000 (
0*
0&
#765000
b1 "
b1 0
b1001101 +
b1101 #
b1101 ,
1*
1&
#770000
b10001 (
0*
0&
#775000
b10 "
b10 0
b1001110 +
b1110 #
b1110 ,
1*
1&
#780000
b10010 (
0*
0&
#785000
b11 "
b11 0
b1001111 +
b1111 #
b1111 ,
1*
1&
#790000
b10011 (
0*
0&
#795000
b101 "
b101 0
01
b101 $
b101 -
b1010000 +
b0 #
b0 ,
1*
1&
#800000
b101 (
0*
0&
#805000
b110 "
b110 0
b1010001 +
b1 #
b1 ,
1*
1&
#810000
b110 (
0*
0&
#815000
b111 "
b111 0
b1010010 +
b10 #
b10 ,
1*
1&
#820000
b111 (
0*
0&
#825000
b1000 "
b1000 0
b1010011 +
b11 #
b11 ,
1*
1&
#830000
b1000 (
0*
0&
#835000
b1001 "
b1001 0
b1010100 +
b100 #
b100 ,
1*
1&
#840000
b1001 (
0*
0&
#845000
b1010 "
b1010 0
b1010101 +
b101 #
b101 ,
1*
1&
#850000
b1010 (
0*
0&
#855000
b1011 "
b1011 0
b1010110 +
b110 #
b110 ,
1*
1&
#860000
b1011 (
0*
0&
#865000
b1100 "
b1100 0
b1010111 +
b111 #
b111 ,
1*
1&
#870000
b1100 (
0*
0&
#875000
b1101 "
b1101 0
b1011000 +
b1000 #
b1000 ,
1*
1&
#880000
b1101 (
0*
0&
#885000
b1110 "
b1110 0
b1011001 +
b1001 #
b1001 ,
1*
1&
#890000
b1110 (
0*
0&
#895000
b1111 "
b1111 0
b1011010 +
b1010 #
b1010 ,
1*
1&
#900000
b1111 (
0*
0&
#905000
b0 "
b0 0
11
b1011011 +
b1011 #
b1011 ,
1*
1&
#910000
b10000 (
0*
0&
#915000
b1 "
b1 0
b1011100 +
b1100 #
b1100 ,
1*
1&
#920000
b10001 (
0*
0&
#925000
b10 "
b10 0
b1011101 +
b1101 #
b1101 ,
1*
1&
#930000
b10010 (
0*
0&
#935000
b11 "
b11 0
b1011110 +
b1110 #
b1110 ,
1*
1&
#940000
b10011 (
0*
0&
#945000
b100 "
b100 0
b1011111 +
b1111 #
b1111 ,
1*
1&
#950000
b10100 (
0*
0&
#955000
b110 "
b110 0
01
b110 $
b110 -
b1100000 +
b0 #
b0 ,
1*
1&
#960000
b110 (
0*
0&
#965000
b111 "
b111 0
b1100001 +
b1 #
b1 ,
1*
1&
#970000
b111 (
0*
0&
#975000
b1000 "
b1000 0
b1100010 +
b10 #
b10 ,
1*
1&
#980000
b1000 (
0*
0&
#985000
b1001 "
b1001 0
b1100011 +
b11 #
b11 ,
1*
1&
#990000
b1001 (
0*
0&
#995000
b1010 "
b1010 0
b1100100 +
b100 #
b100 ,
1*
1&
#1000000
b1010 (
0*
0&
#1005000
b1011 "
b1011 0
b1100101 +
b101 #
b101 ,
1*
1&
